Códigos/Display2.v
module Display2(
		input wire clock,
		input wire start,
		input wire finish,
		input wire [7:0] c1,
		input wire [7:0] c2,
		input	wire [7:0] nulo,	
		output reg [6:0] display1,
		output reg [6:0] display2,
		output reg [6:0] displayCem,
		output reg [6:0] displayDez,
		output reg [6:0] displayUm
);
	parameter S0 = 0; //LuLa;
	parameter S1 = 1; //Bozo;
	parameter S2 = 2; //Nulo;
	
	reg [6:0] next_state;
	reg [6:0] state;
	
	always @(posedge finish)
	begin
		if(finish)
			state = next_state;
	end
		
	always @(posedge clock)begin
		if(start)
		begin
			display1 <= 7'b1111111;
			display2 <= 7'b1111111;
			displayCem <= 7'b1111111;
			displayDez <= 7'b1111111;
			displayUm <= 7'b1111111;
			next_state = S0;
		end
		else if(finish)
		begin
		case(state)
		S0:
		begin
		//Exibição dos votos de Lula
		display1 <= 7'b1111001;
		display2 <= 7'b0110000;
					
					//Atribuição da centena
					case(c1 / 100)
						//Algarismos
						0: displayCem = 7'b1000000;
						1: displayCem = 7'b1111001;
						2: displayCem = 7'b0100100;
					endcase
					//Atribuição da dezena
					case((c1 % 100) / 10)
						//Algarismos
						0: displayDez = 7'b1000000;
						1: displayDez = 7'b1111001;
						2: displayDez = 7'b0100100;
						3: displayDez = 7'b0110000;
						4: displayDez = 7'b0011001;
						5: displayDez = 7'b0010010;
						6: displayDez = 7'b0000010;
						7: displayDez = 7'b1111000;
						8: displayDez = 7'b0000000;
						9: displayDez = 7'b0010000;
					endcase
					//Atribuição da unidade
					case((c1 % 100) % 10)
						//Algarismos
						0: displayUm = 7'b1000000;
						1: displayUm = 7'b1111001;
						2: displayUm = 7'b0100100;
						3: displayUm = 7'b0110000;
						4: displayUm = 7'b0011001;
						5: displayUm = 7'b0010010;
						6: displayUm = 7'b0000010;
						7: displayUm = 7'b1111000;
						8: displayUm = 7'b0000000;
						9: displayUm = 7'b0010000;
					endcase
					next_state = S1;
		end
		S1:
		begin
				//Exibição dos votos de Jair Genocida Bolsonaro
				display1 <= 7'b0100100;
				display2 <= 7'b0100100;
				
				//Atribuição da centena
				case(c2 / 100)
					//Algarismos
					0: displayCem = 7'b1000000;
					1: displayCem = 7'b1111001;
					2: displayCem = 7'b0100100;
				endcase
				//Atribuição da dezena
				case((c2 % 100) / 10)
					//Algarismos
					0: displayDez = 7'b1000000;
					1: displayDez = 7'b1111001;
					2: displayDez = 7'b0100100;
					3: displayDez = 7'b0110000;
					4: displayDez = 7'b0011001;
					5: displayDez = 7'b0010010;
					6: displayDez = 7'b0000010;
					7: displayDez = 7'b1111000;
					8: displayDez = 7'b0000000;
					9: displayDez = 7'b0010000;
				endcase
				//Atribuição da unidade
				case((c2 % 100) % 10)
					//Algarismos
					0: displayUm = 7'b1000000;
					1: displayUm = 7'b1111001;
					2: displayUm = 7'b0100100;
					3: displayUm = 7'b0110000;
					4: displayUm = 7'b0011001;
					5: displayUm = 7'b0010010;
					6: displayUm = 7'b0000010;
					7: displayUm = 7'b1111000;
					8: displayUm = 7'b0000000;
					9: displayUm = 7'b0010000;
				endcase
				next_state = S2;
			end
		S2:
			begin
				//Exibição dos votos anulados
				display1 <= 7'b1000000;
				display2 <= 7'b1000000; 
				
				//Atribuição da centena
				case(nulo / 100)
					//Algarismos
					0: displayCem = 7'b1000000;
					1: displayCem = 7'b1111001;
					2: displayCem = 7'b0100100;
				endcase
				//Atribuição da dezena
				case((nulo % 100) / 10)
					//Algarismos
					0: displayDez = 7'b1000000;
					1: displayDez = 7'b1111001;
					2: displayDez = 7'b0100100;
					3: displayDez = 7'b0110000;
					4: displayDez = 7'b0011001;
					5: displayDez = 7'b0010010;
					6: displayDez = 7'b0000010;
					7: displayDez = 7'b1111000;
					8: displayDez = 7'b0000000;
					9: displayDez = 7'b0010000;
				endcase
				//Atribuição da unidade
				case((nulo % 100) % 10)
					//Algarismos
					0: displayUm = 7'b1000000;
					1: displayUm = 7'b1111001;
					2: displayUm = 7'b0100100;
					3: displayUm = 7'b0110000;
					4: displayUm = 7'b0011001;
					5: displayUm = 7'b0010010;
					6: displayUm = 7'b0000010;
					7: displayUm = 7'b1111000;
					8: displayUm = 7'b0000000;
					9: displayUm = 7'b0010000;
				endcase
				next_state = S0;
				end
		endcase
		end
	end
endmodule

Códigos/Display1.v
module Display(
		input [3:0] dig1,
		
		output reg [6:0] display1
);
	always @(dig1)
		case(dig1)
		4'b0000:
			display1 = 7'b1000000;
			
		4'b0001:
			display1 = 7'b1111001;
			
		4'b0010:
			display1 = 7'b0100100;
			
		4'b0011:
			display1 = 7'b0110000;
			
		4'b0100:
			display1 = 7'b0011001;
			
		4'b0101:
			display1 = 7'b0010010;
			
		4'b0110:
			display1 = 7'b0000010;
			
		4'b0111:
			display1 = 7'b1111000;
			
		4'b1000:
			display1 =7'b0000000;
			
		4'b1001:
			display1 = 7'b0010000;
			
		4'b1111:
			display1 = 7'b1111111;
		4'b1101:
			display1 = 7'b1110111;
		endcase
endmodule

Códigos/FSM.v
module test(clock, digit, valid, start, state, next_state, finish, swap, digit1, digit2, vote_status, C1, C2, Nulo);

	input wire clock;
	
	input wire [3:0] digit;
	
	input wire valid;
	input wire start;
	input wire finish;
	input wire swap;
	
	output reg [3:0] digit1;
	output reg [3:0] digit2;
	
	output reg [1:0] vote_status;
	output reg [3:0] state;
	output reg [3:0] next_state;
	
	output reg [7:0] C1;
	output reg [7:0] C2;
	output reg [7:0] Nulo;
	 
	parameter S0 = 0; //Inicio do voto;
	parameter S1 = 1; //Entrada 1;
	parameter S2 = 2; //Entrada 2;
	parameter S3 = 3; //Entrada !1 e !2;
	parameter S4 = 4; //Entrada 3 apos S1 // voto valido
	parameter S5 = 5;// Entrada 2 apos S2 // voto valido
	parameter S6 = 6; // voto nulo
	
	always @(posedge clock)begin
	if(finish) state = S0;
	else if(start) 
	begin
		digit1 = 4'b1101;
		digit2 = 4'b1101;
		state = S0;
		C1 = 7'b0000000;
		C2 = 7'b0000000;
		Nulo = 7'b0000000;
	end
	else if(valid) 
	begin
		if(state == S0) digit1 = digit;
		else if(state == S1) digit2 = digit;
		else if(state == S2) digit2 = digit;
		else if(state == S3) digit2 = digit;
		if(state == S4) 
		begin
			digit1 = 4'b1101;
			digit2 = 4'b1101;
			if(swap) C2 <= C2 + 7'b0000001;
			else C1 <= C1 + 7'b0000001;
		end
		else if(state == S5) 
		begin
			digit1 = 4'b1101;
			digit2 = 4'b1101;
			if(swap) C1 <= C1 + 7'b0000001;
			else C2 <= C2 + 7'b0000001;
		end
		else if(state == S6) 
		begin
			digit1 = 4'b1101;
			digit2 = 4'b1101;
			Nulo <= Nulo + 7'b0000001;
		end
		state = next_state;
	end
end

always @(posedge valid)begin
	if(state == S0)
	begin
		vote_status = 2'b00;
		if(digit == 4'b0001) next_state = S1;
		else if (digit == 4'b0010) next_state = S2;
		else next_state = S3;
	end
	
	else if(state == S1)
	begin
		if(digit == 4'b0011) next_state = S4;
		else next_state = S6;
	end
	
	else if(state == S2)
	begin
		if(digit == 4'b0010) next_state = S5;
		else next_state = S6;
	end
	
	else if(state == S3)
	begin
		next_state = S6;
	end
	
	else if(state == S4)
	begin 
		vote_status = 2'b01;
		next_state = S0;
	end	
	else if(state == S5)
	begin
		vote_status = 2'b01;
		next_state = S0;
	end
	else if(state == S6)
	begin
		vote_status = 2'b10;
		next_state = S0;
	end

end


endmodule

Testbench/Eleicao2.v
`include "FSM.v"
`include "Display1.v"
`include "Display2.v"
module Eleicao;
	
	reg clk = 0;
	reg [3:0] digit = 0;
	reg valid = 0;
	reg finish = 0;
	reg start = 0;
	reg swap = 0;
	
	wire [3:0] dig1;
	wire [3:0] dig2;
	
	wire [1:0] vote_status;
	wire [3:0] state;
	wire [7:0] C1;
	wire [7:0] C2;
	wire [7:0] Nulo;
	wire [7:0] contC1;
	wire [7:0] contC2;
	wire [7:0] contNulo;
	wire [3:0] next_state;
	
	wire [6:0] display1;
	wire [6:0] display2;
	wire [6:0] dis1;
	wire [6:0] dis2;
	wire [6:0] displayCem;
	wire [6:0] displayDez;
	wire [6:0] displayUm;	
	
	test t(
		.clock(clk), 
		.digit(digit), 
		.valid(valid),
		.finish(finish),
		.start(start),
		.swap(swap),
		
		.digit1(dig1),
		.digit2(dig2),
		.vote_status(vote_status),
		.state(state),
		.C1(C1),
		.C2(C2),
		.Nulo(Nulo)
		);
	
	Display d1(
		.dig1(dig1),
		.display1(dis1)
		);
	
	Display d2(
		.dig1(dig2),
		.display1(dis2)
		);
	
	Display2 um(
		.clock(clk),
		.finish(finish),
		.start(start),
		.c1(C1),
		.c2(C2),
		.nulo(Nulo),	
		.display1(display1),
		.display2(display2),
		.displayCem(displayCem),
		.displayDez(displayDez),
		.displayUm(displayUm)
		);
	
	always #1 clk = ~clk;
	
	always
	begin
		#1 $display("  %b   |   %b  |   %b   |    %b   |   %b   | %b |      %b     |  %b  | %b | %b |%d |%d | %d  |  %0t", clk, swap, valid, finish, start, state, vote_status, digit, dig1, dig2, C1, C2, Nulo, $time);
	end
	
	//always #1 $display("clk: %b", clk);
	
	initial begin
		#0 $dumpfile("apuracao.vcd");
		#0 $dumpvars(0, Eleicao);
		#0 $display("Clock | Swap | Valid | Finish | Start |  State  | Vote Status | Digito | dig1 | dig2 | C1 | C2 | Nulo | Time ");
		
		//Inicio da primeira eleicao
			//t = 0
			#0 $display("Inicio da primeira eleicao");
			#0 start = 1;
			#0 valid = 1;
			
			//t = 2
			#2 valid = 0;
			#0 start = 0;
		
		//Insercao do digito 9
			//t = 4
			#2 $display("\n\nInsercao do digito 9");
			#0 digit = 9;
			#0 valid = 1;
			
			//t = 6
			#2 valid = 0;
		
		//Insercao do dígito 1
			//t = 8
			#2 $display("Insercao do digito 1");
			#0 digit = 1;
			#0 valid = 1;
			
			//t = 10
			#2 valid = 0;
		
		//Confirmacao do voto 91
			//t = 12
			#2 $display("Confirmacao do voto 91");
			#0 valid = 1;
			
			//t = 14
			#2 valid = 0;
		
		//Insercao do digito 1
			//t = 16
			#2 $display("\n\nInsercao do digito 1");
			#0 digit = 1;
			#0 valid = 1;
			
			//t = 18
			#2 valid = 0;
		
		//Insercao do digito 3
			//t = 20
			#2 $display("Insercao do digito 3");
			#0 digit = 3;
			#0 valid = 1;
			
			//t = 22
			#2 valid = 0;
		
		//Confirmacao do voto 13
			//t = 24
			#2 $display("Confirmacao do voto 13");
			#0 valid = 1;
			
			//t = 26
			#2 valid = 0;
		
		//Finalizacao da eleicao 1, exibicao dos votos do lula
			//t = 28
			#2 $display("\n\nFinalizacao da eleicao 1, exibicao dos votos do lula");
			#0 finish = 1;
			
			//t = 30
			#2 finish = 0;
		
		//Exibicao dos votos do bolsonaro
			//t = 32
			#2 $display("Exibicao dos votos do bolsonaro");
			#0 finish = 1;
			
			//t = 34
			#2 finish = 0;
		
		//Exibicao dos votos nulos
			//t = 36
			#2 $display("Exibicao dos votos nulos");
			#0 finish = 1;
			
			//t = 38
			#2 finish = 0;
		
		//Início da segunda eleicao
			//t = 40
			#2 $display("\n\nInicio da segunda eleicao");
			#0 start = 1;
			#0 valid = 1;
			
			//t = 42
			#2 valid = 0;
			#0 start = 0;
		
		//Insercao do digito 5
			//t = 44
			#2 $display("\n\nInsercao do digito 5");
			#0 digit = 5;
			#0 valid = 1;
			
			//t = 46
			#2 valid = 0;
		
		//Insercao do digito 1
			//t = 48
			#2 $display("Insercao do digito 1");
			#0 digit = 1;
			#0 valid = 1;
			
			//t = 50
			#2 valid = 0;
		
		//Confirmacao do voto 51
			//t = 52
			#2 $display("Confirmacao do voto 51");
			#0 valid = 1;
			
			//t = 54
			#2 valid = 0;
		
		//Insercao do digito 1
			//t = 56
			#2 $display("\n\nInsercao do digito 1");
			#0 digit = 1;
			#0 valid = 1;
			
			//t = 58
			#2 valid = 0;
		
		//Insercao do digito 3
			//t = 60
			#2 $display("Insercao do digito 3");
			#0 digit = 3;
			#0 valid = 1;
			
			//t = 62
			#2 valid = 0;
		
		//Confirmacao do voto 13
			//t = 64
			#2 $display("Confirmacao do voto 13");
			#0 valid = 1;
			
			//t = 66
			#2 valid = 0;
		
		//Insercao do digito 2
			//t = 68
			#2 $display("\n\nInsercao do digito 2");
			#0 digit = 2;
			#0 valid = 1;
			
			//t = 70
			#2 valid = 0;
		
		//Insercao do digito 2
			//t = 72
			#2 $display("Insercao do digito 2");
			#0 valid = 1;
			
			//t = 74
			#2 valid = 0;
		
		//Confirmacao do voto 22
			//t = 76
			#2 $display("Confirmacao do voto 22");
			#0 valid = 1;
			
			//t = 78
			#2 valid = 0;
		
		//Insercao do digito 1
			//t = 80
			#2 $display("\n\nInsercao do digito 1");
			#0 digit = 1;
			#0 valid = 1;
			
			//t = 82
			#2 valid = 0;
		
		//Insercao do digito 3
			//t = 84
			#2 $display("Insercao do digito 3");
			#0 digit = 3;
			#0 valid = 1;
			
			//t = 86
			#2 valid = 0;
		
		//Confirmacao do voto 13
			//t = 88
			#2 $display("Confirmacao do voto 13");
			#0 valid = 1;
			
			//t = 90
			#2 valid = 0;
		
		//Insercao do digito 2
			//t = 92
			#2 $display("\n\nInsercao do digito 2");
			#0 digit = 2;
			#0 valid = 1;
			
			//t = 94
			#2 valid = 0;
		
		//Insercao do digito 0
			//t = 96
			#2 $display("Insercao do digito 0");
			#0 digit = 0;
			#0 valid = 1;
			
			//t = 98
			#2 valid = 0;
		
		//Confirmacao do voto 20
			//t = 100
			#2 $display("Confirmacao do voto 20");
			#0 valid = 1;
			
			//t = 102
			#2 valid = 0;
		
		//Insercao do digito 1
			//t = 104
			#2 $display("\n\nInsercao do digito 1");
			#0 digit = 1;
			#0 valid = 1;
			
			//t = 106
			#2 valid = 0;
		
		//Insercao do digito 2
			//t = 108
			#2 $display("Insercao do digito 2");
			#0 digit = 2;
			#0 valid = 1;
			
			//t = 110
			#2 valid = 0;
		
		//Confirmacao do voto 12
			//t = 112
			#2 $display("Confirmacao do voto 12");
			#0 valid = 1;
			
			//t = 114
			#2 valid = 0;
		
		//Insercao do digito 1 e ativacao do swap
			//t = 116
			#2 $display("\n\nInsercao do digito 1 e ativacao do swap");
			#0 swap = 1;
			#0 digit = 1;
			#0 valid = 1;
			
			//t = 118
			#2 valid = 0;
		
		//Insercao do dígito 3
			//t = 120
			#2 $display("Insercao do digito 3");
			#0 digit = 3;
			#0 valid = 1;
			
			//t = 122
			#2 valid = 0;
		
		//Confirmacao do voto 13 com swap ativo
			//t = 124
			#2 $display("Confirmacao do voto 13 (swapped)");
			#0 valid = 1;
			
			//t = 126
			#2 valid = 0;
		
		//Insercao do digito 2
			//t = 128
			#2 $display("\n\nInsercao do digito 2 (swap ainda ativo)");
			#0 digit = 2;
			#0 valid = 1;
			
			//t = 130
			#2 valid = 0;
		
		//Insercao do digito 3
			//t = 132
			#2 $display("Insercao do digito 2");
			#0 digit = 2;
			#0 valid = 1;
			
			//t = 134
			#2 valid = 0;
		
		//Confirmacao do voto 13 com swap ativo
			//t = 136
			#2 $display("Confirmacao do voto 22 (swapped)");
			#0 valid = 1;
			
			//t = 138
			#2 valid = 0;
		
		//Finalizacao da eleicao 2, exibicao dos votos do lula
			//t = 140
			#2 $display("\n\nFinalizacao da eleicao 2, exibicao dos votos do lula");
			#0 finish = 1;
			
			//t = 142
			#2 finish = 0;
		
		//Exibicao dos votos do bolsonaro
			//t = 144
			#2 $display("Exibicao dos votos do bolsonaro");
			#0 finish = 1;
			
			//t = 146
			#2 finish = 0;
		
		//Exibicao dos votos nulos
			//t = 148
			#2 $display("Exibicao dos votos nulos");
			#0 finish = 1;
			
			//t = 150
			#2 finish = 0;
				
		//Fim da simulacao
			//t = 152
			#2 $finish;
	end

endmodule

Ondas/apuracao.vcd
$date
	Wed Dec 07 03:31:55 2022
$end
$version
	Icarus Verilog
$end
$timescale
	1s
$end
$scope module Eleicao $end
$var wire 2 ! vote_status [1:0] $end
$var wire 4 " state [3:0] $end
$var wire 7 # displayUm [6:0] $end
$var wire 7 $ displayDez [6:0] $end
$var wire 7 % displayCem [6:0] $end
$var wire 7 & display2 [6:0] $end
$var wire 7 ' display1 [6:0] $end
$var wire 7 ( dis2 [6:0] $end
$var wire 7 ) dis1 [6:0] $end
$var wire 4 * dig2 [3:0] $end
$var wire 4 + dig1 [3:0] $end
$var wire 8 , Nulo [7:0] $end
$var wire 8 - C2 [7:0] $end
$var wire 8 . C1 [7:0] $end
$var reg 1 / clk $end
$var reg 4 0 digit [3:0] $end
$var reg 1 1 finish $end
$var reg 1 2 start $end
$var reg 1 3 swap $end
$var reg 1 4 valid $end
$scope module d1 $end
$var wire 4 5 dig1 [3:0] $end
$var reg 7 6 display1 [6:0] $end
$upscope $end
$scope module d2 $end
$var wire 4 7 dig1 [3:0] $end
$var reg 7 8 display1 [6:0] $end
$upscope $end
$scope module t $end
$var wire 1 / clock $end
$var wire 4 9 digit [3:0] $end
$var wire 1 1 finish $end
$var wire 1 2 start $end
$var wire 1 3 swap $end
$var wire 1 4 valid $end
$var parameter 32 : S0 $end
$var parameter 32 ; S1 $end
$var parameter 32 < S2 $end
$var parameter 32 = S3 $end
$var parameter 32 > S4 $end
$var parameter 32 ? S5 $end
$var parameter 32 @ S6 $end
$var reg 8 A C1 [7:0] $end
$var reg 8 B C2 [7:0] $end
$var reg 8 C Nulo [7:0] $end
$var reg 4 D digit1 [3:0] $end
$var reg 4 E digit2 [3:0] $end
$var reg 4 F next_state [3:0] $end
$var reg 4 G state [3:0] $end
$var reg 2 H vote_status [1:0] $end
$upscope $end
$scope module um $end
$var wire 8 I c1 [7:0] $end
$var wire 8 J c2 [7:0] $end
$var wire 1 / clock $end
$var wire 1 1 finish $end
$var wire 8 K nulo [7:0] $end
$var wire 1 2 start $end
$var parameter 32 L S0 $end
$var parameter 32 M S1 $end
$var parameter 32 N S2 $end
$var reg 7 O display1 [6:0] $end
$var reg 7 P display2 [6:0] $end
$var reg 7 Q displayCem [6:0] $end
$var reg 7 R displayDez [6:0] $end
$var reg 7 S displayUm [6:0] $end
$var reg 7 T next_state [6:0] $end
$var reg 7 U state [6:0] $end
$upscope $end
$upscope $end
$enddefinitions $end
$comment Show the parameter values. $end
$dumpall
b10 N
b1 M
b0 L
b110 @
b101 ?
b100 >
b11 =
b10 <
b1 ;
b0 :
$end
#0
$dumpvars
bx U
bx T
bx S
bx R
bx Q
bx P
bx O
bx K
bx J
bx I
bx H
bx G
bx F
bx E
bx D
bx C
bx B
bx A
b0 9
bx 8
bx 7
bx 6
bx 5
14
03
12
01
b0 0
0/
bx .
bx -
bx ,
bx +
bx *
bx )
bx (
bx '
bx &
bx %
bx $
bx #
bx "
bx !
$end
#1
b1111111 #
b1111111 S
b1111111 $
b1111111 R
b1111111 %
b1111111 Q
b1111111 &
b1111111 P
b1111111 '
b1111111 O
b1110111 (
b1110111 8
b1110111 )
b1110111 6
b0 ,
b0 C
b0 K
b0 -
b0 B
b0 J
b0 .
b0 A
b0 I
b0 "
b0 G
b1101 *
b1101 7
b1101 E
b1101 +
b1101 5
b1101 D
b0 T
1/
#2
02
0/
04
#3
1/
#4
b11 F
b0 !
b0 H
14
b1001 0
b1001 9
0/
#5
b10000 )
b10000 6
b11 "
b11 G
b1001 +
b1001 5
b1001 D
1/
#6
0/
04
#7
1/
#8
b110 F
14
b1 0
b1 9
0/
#9
b1111001 (
b1111001 8
b110 "
b110 G
b1 *
b1 7
b1 E
1/
#10
0/
04
#11
1/
#12
b0 F
b10 !
b10 H
14
0/
#13
b1 ,
b1 C
b1 K
b1110111 (
b1110111 8
b1110111 )
b1110111 6
b0 "
b0 G
b1101 *
b1101 7
b1101 E
b1101 +
b1101 5
b1101 D
1/
#14
0/
04
#15
1/
#16
b1 F
b0 !
b0 H
14
0/
#17
b1111001 )
b1111001 6
b1 "
b1 G
b1 +
b1 5
b1 D
1/
#18
0/
04
#19
1/
#20
b100 F
14
b11 0
b11 9
0/
#21
b110000 (
b110000 8
b100 "
b100 G
b11 *
b11 7
b11 E
1/
#22
0/
04
#23
1/
#24
b0 F
b1 !
b1 H
14
0/
#25
b1 .
b1 A
b1 I
b1110111 (
b1110111 8
b1110111 )
b1110111 6
b0 "
b0 G
b1101 *
b1101 7
b1101 E
b1101 +
b1101 5
b1101 D
1/
#26
0/
04
#27
1/
#28
b0 U
11
0/
#29
b110000 &
b110000 P
b1111001 '
b1111001 O
b1 T
b1111001 #
b1111001 S
b1000000 $
b1000000 R
b1000000 %
b1000000 Q
1/
#30
0/
01
#31
1/
#32
b1 U
11
0/
#33
b100100 &
b100100 P
b100100 '
b100100 O
b10 T
b1000000 #
b1000000 S
1/
#34
0/
01
#35
1/
#36
b10 U
11
0/
#37
b1000000 &
b1000000 P
b1000000 '
b1000000 O
b0 T
b1111001 #
b1111001 S
1/
#38
0/
01
#39
1/
#40
b11 F
b0 !
b0 H
14
12
0/
#41
b1111111 #
b1111111 S
b1111111 $
b1111111 R
b1111111 %
b1111111 Q
b1111111 &
b1111111 P
b1111111 '
b1111111 O
b0 ,
b0 C
b0 K
b0 .
b0 A
b0 I
1/
#42
02
0/
04
#43
1/
#44
14
b101 0
b101 9
0/
#45
b10010 )
b10010 6
b11 "
b11 G
b101 +
b101 5
b101 D
1/
#46
0/
04
#47
1/
#48
b110 F
14
b1 0
b1 9
0/
#49
b1111001 (
b1111001 8
b110 "
b110 G
b1 *
b1 7
b1 E
1/
#50
0/
04
#51
1/
#52
b0 F
b10 !
b10 H
14
0/
#53
b1 ,
b1 C
b1 K
b1110111 (
b1110111 8
b1110111 )
b1110111 6
b0 "
b0 G
b1101 *
b1101 7
b1101 E
b1101 +
b1101 5
b1101 D
1/
#54
0/
04
#55
1/
#56
b1 F
b0 !
b0 H
14
0/
#57
b1111001 )
b1111001 6
b1 "
b1 G
b1 +
b1 5
b1 D
1/
#58
0/
04
#59
1/
#60
b100 F
14
b11 0
b11 9
0/
#61
b110000 (
b110000 8
b100 "
b100 G
b11 *
b11 7
b11 E
1/
#62
0/
04
#63
1/
#64
b0 F
b1 !
b1 H
14
0/
#65
b1 .
b1 A
b1 I
b1110111 (
b1110111 8
b1110111 )
b1110111 6
b0 "
b0 G
b1101 *
b1101 7
b1101 E
b1101 +
b1101 5
b1101 D
1/
#66
0/
04
#67
1/
#68
b10 F
b0 !
b0 H
14
b10 0
b10 9
0/
#69
b100100 )
b100100 6
b10 "
b10 G
b10 +
b10 5
b10 D
1/
#70
0/
04
#71
1/
#72
b101 F
14
0/
#73
b100100 (
b100100 8
b101 "
b101 G
b10 *
b10 7
b10 E
1/
#74
0/
04
#75
1/
#76
b0 F
b1 !
b1 H
14
0/
#77
b1 -
b1 B
b1 J
b1110111 (
b1110111 8
b1110111 )
b1110111 6
b0 "
b0 G
b1101 *
b1101 7
b1101 E
b1101 +
b1101 5
b1101 D
1/
#78
0/
04
#79
1/
#80
b1 F
b0 !
b0 H
14
b1 0
b1 9
0/
#81
b1111001 )
b1111001 6
b1 "
b1 G
b1 +
b1 5
b1 D
1/
#82
0/
04
#83
1/
#84
b100 F
14
b11 0
b11 9
0/
#85
b110000 (
b110000 8
b100 "
b100 G
b11 *
b11 7
b11 E
1/
#86
0/
04
#87
1/
#88
b0 F
b1 !
b1 H
14
0/
#89
b10 .
b10 A
b10 I
b1110111 (
b1110111 8
b1110111 )
b1110111 6
b0 "
b0 G
b1101 *
b1101 7
b1101 E
b1101 +
b1101 5
b1101 D
1/
#90
0/
04
#91
1/
#92
b10 F
b0 !
b0 H
14
b10 0
b10 9
0/
#93
b100100 )
b100100 6
b10 "
b10 G
b10 +
b10 5
b10 D
1/
#94
0/
04
#95
1/
#96
b110 F
14
b0 0
b0 9
0/
#97
b1000000 (
b1000000 8
b110 "
b110 G
b0 *
b0 7
b0 E
1/
#98
0/
04
#99
1/
#100
b0 F
b10 !
b10 H
14
0/
#101
b10 ,
b10 C
b10 K
b1110111 (
b1110111 8
b1110111 )
b1110111 6
b0 "
b0 G
b1101 *
b1101 7
b1101 E
b1101 +
b1101 5
b1101 D
1/
#102
0/
04
#103
1/
#104
b1 F
b0 !
b0 H
14
b1 0
b1 9
0/
#105
b1111001 )
b1111001 6
b1 "
b1 G
b1 +
b1 5
b1 D
1/
#106
0/
04
#107
1/
#108
b110 F
14
b10 0
b10 9
0/
#109
b100100 (
b100100 8
b110 "
b110 G
b10 *
b10 7
b10 E
1/
#110
0/
04
#111
1/
#112
b0 F
b10 !
b10 H
14
0/
#113
b11 ,
b11 C
b11 K
b1110111 (
b1110111 8
b1110111 )
b1110111 6
b0 "
b0 G
b1101 *
b1101 7
b1101 E
b1101 +
b1101 5
b1101 D
1/
#114
0/
04
#115
1/
#116
b1 F
b0 !
b0 H
14
b1 0
b1 9
13
0/
#117
b1111001 )
b1111001 6
b1 "
b1 G
b1 +
b1 5
b1 D
1/
#118
0/
04
#119
1/
#120
b100 F
14
b11 0
b11 9
0/
#121
b110000 (
b110000 8
b100 "
b100 G
b11 *
b11 7
b11 E
1/
#122
0/
04
#123
1/
#124
b0 F
b1 !
b1 H
14
0/
#125
b10 -
b10 B
b10 J
b1110111 (
b1110111 8
b1110111 )
b1110111 6
b0 "
b0 G
b1101 *
b1101 7
b1101 E
b1101 +
b1101 5
b1101 D
1/
#126
0/
04
#127
1/
#128
b10 F
b0 !
b0 H
14
b10 0
b10 9
0/
#129
b100100 )
b100100 6
b10 "
b10 G
b10 +
b10 5
b10 D
1/
#130
0/
04
#131
1/
#132
b101 F
14
0/
#133
b100100 (
b100100 8
b101 "
b101 G
b10 *
b10 7
b10 E
1/
#134
0/
04
#135
1/
#136
b0 F
b1 !
b1 H
14
0/
#137
b11 .
b11 A
b11 I
b1110111 (
b1110111 8
b1110111 )
b1110111 6
b0 "
b0 G
b1101 *
b1101 7
b1101 E
b1101 +
b1101 5
b1101 D
1/
#138
0/
04
#139
1/
#140
b0 U
11
0/
#141
b110000 &
b110000 P
b1111001 '
b1111001 O
b1 T
b110000 #
b110000 S
b1000000 $
b1000000 R
b1000000 %
b1000000 Q
1/
#142
0/
01
#143
1/
#144
b1 U
11
0/
#145
b100100 &
b100100 P
b100100 '
b100100 O
b10 T
b100100 #
b100100 S
1/
#146
0/
01
#147
1/
#148
b10 U
11
0/
#149
b1000000 &
b1000000 P
b1000000 '
b1000000 O
b0 T
b110000 #
b110000 S
1/
#150
0/
01
